aiogremlin/__init__.py
aiogremlin/exception.py
aiogremlin/driver/__init__.py
aiogremlin/driver/client.py
aiogremlin/driver/cluster.py
aiogremlin/driver/connection.py
aiogremlin/driver/pool.py
aiogremlin/driver/protocol.py
aiogremlin/driver/provider.py
aiogremlin/driver/resultset.py
aiogremlin/driver/server.py
aiogremlin/driver/aiohttp/__init__.py
aiogremlin/driver/aiohttp/transport.py
aiogremlin/process/__init__.py
aiogremlin/process/graph_traversal.py
aiogremlin/process/traversal.py
aiogremlin/remote/__init__.py
aiogremlin/remote/driver_remote_connection.py
aiogremlin/remote/driver_remote_side_effects.py
aiogremlin/remote/remote_connection.py
aiogremlin/structure/__init__.py
aiogremlin/structure/graph.py
aiogremlin-3.3.4.dist-info/LICENSE
aiogremlin-3.3.4.dist-info/METADATA
aiogremlin-3.3.4.dist-info/NOTICE
aiogremlin-3.3.4.dist-info/WHEEL
aiogremlin-3.3.4.dist-info/top_level.txt
aiogremlin-3.3.4.dist-info/RECORD
