Metadata-Version: 2.1
Name: aiogremlin
Version: 3.3.4
Summary: An asynchronous DSL for the Gremlin-Python driver
Home-page: http://goblin-ogm.com
Author: Jeffrey Phillips Freeman
Author-email: Jeffrey.Freeman@CleverThis.com
License: Apache License, Version 2.0
Download-URL: https://github.com/goblin-ogm/aiogremlin/archive/v3.3.4.tar.gz
Keywords: Tinkerpop,Tinkerpop3,gremlin,gremlin-python,asyncio,graphdb
Platform: UNKNOWN
Classifier: Development Status :: 5 - Production/Stable
Classifier: Intended Audience :: Developers
Classifier: License :: OSI Approved :: Apache Software License
Classifier: Operating System :: OS Independent
Classifier: Programming Language :: Python
Classifier: Programming Language :: Python :: 3
Classifier: Programming Language :: Python :: 3.5
Classifier: Programming Language :: Python :: 3.6
Classifier: Programming Language :: Python :: 3.7
Classifier: Programming Language :: Python :: 3.8
Classifier: Programming Language :: Python :: Implementation :: PyPy
Requires-Python: >=3.5
Requires-Dist: gremlinpython (<=3.4.3)
Requires-Dist: aenum (>=1.4.5)
Requires-Dist: aiohttp (>=2.2.5)
Requires-Dist: PyYAML (>=3.12)
Requires-Dist: six (>=1.10.0)
Requires-Dist: inflection (>=0.3.1)
